MANIFEST.in
RELEASE-VERSION
pavement.py
paver-minilib.zip
setup.py
version.py
arduino_array/__init__.py
arduino_array.egg-info/PKG-INFO
arduino_array.egg-info/SOURCES.txt
arduino_array.egg-info/dependency_links.txt
arduino_array.egg-info/top_level.txt
arduino_array/Arduino/Array/Array.h
arduino_array/lib/Array-Arduino.tar.gz