Metadata-Version: 1.0
Name: arduino-array
Version: 0.1
Summary: Simple C classes for arrays of standard numeric types.
Home-page: https://github.com/wheeler-microfluidics/arduino-array
Author: Christian Fobel
Author-email: christian@fobel.net
License: GPL
Keywords: arduino c++ array simple
Platform: UNKNOWN
